hard_pil/__init__.py
hard_pil/_version.py
hard_pil/aio_editor.py
hard_pil/canvas.py
hard_pil/editor.py
hard_pil/font.py
hard_pil/fonts/BarlowCondensed/BarlowCondensed-Bold.ttf
hard_pil/fonts/BarlowCondensed/BarlowCondensed-Italic.ttf
hard_pil/fonts/BarlowCondensed/BarlowCondensed-Light.ttf
hard_pil/fonts/BarlowCondensed/BarlowCondensed-Regular.ttf
hard_pil/fonts/caveat/caveat.ttf
hard_pil/fonts/Lato/Lato-Bold.ttf
hard_pil/fonts/Lato/Lato-Italic.ttf
hard_pil/fonts/Lato/Lato-Light.ttf
hard_pil/fonts/Lato/Lato-Regular.ttf
hard_pil/fonts/montserrat/montserrat_bold.ttf
hard_pil/fonts/montserrat/montserrat_italic.ttf
hard_pil/fonts/montserrat/montserrat_light.ttf
hard_pil/fonts/montserrat/montserrat_regular.ttf
hard_pil/fonts/poppins/poppins_bold.ttf
hard_pil/fonts/poppins/poppins_italic.ttf
hard_pil/fonts/poppins/poppins_light.ttf
hard_pil/fonts/poppins/poppins_regular.ttf
hard_pil/gif_editor.py
hard_pil/text.py
hard_pil/types/__init__.py
hard_pil/types/common.py
hard_pil/types/workspace.py
hard_pil/utils.py
hard_pil/workspace.py
hard_pil-0.3.2.dist-info/LICENSE
hard_pil-0.3.2.dist-info/METADATA
hard_pil-0.3.2.dist-info/WHEEL
hard_pil-0.3.2.dist-info/RECORD
